publishmd/__init__.py
publishmd/base.py
publishmd/cli.py
publishmd/config.py
publishmd/processor.py
publishmd/emitters/__init__.py
publishmd/emitters/assets_emitter.py
publishmd/emitters/qmd_emitter.py
publishmd/filters/__init__.py
publishmd/filters/frontmatter_filter.py
publishmd/transformers/__init__.py
publishmd/transformers/stale_links_transformer.py
publishmd/transformers/tags_to_categories_transformer.py
publishmd/transformers/wikilink_transformer.py
publishmd-0.1.0.dist-info/METADATA
publishmd-0.1.0.dist-info/WHEEL
publishmd-0.1.0.dist-info/entry_points.txt
publishmd-0.1.0.dist-info/top_level.txt
publishmd-0.1.0.dist-info/RECORD
