Metadata-Version: 2.4
Name: publishmd
Version: 0.1.0
Summary: Prepare markdown content for publication with configurable processing pipeline
Author: Mateus Molina
License-Expression: MIT
Project-URL: Homepage, https://github.com/MateusMolina/publishmd
Project-URL: Repository, https://github.com/MateusMolina/publishmd.git
Project-URL: Issues, https://github.com/MateusMolina/publishmd/issues
Keywords: quarto,markdown,publishing,second-brain,notes,vault,obsidian,journal
Classifier: Development Status :: 4 - Beta
Classifier: Programming Language :: Python :: 3
Classifier: Topic :: Office/Business
Requires-Python: >=3.10
Requires-Dist: pyyaml>=6.0
Requires-Dist: click>=8.0
Provides-Extra: dev
Requires-Dist: pytest; extra == "dev"
Requires-Dist: black; extra == "dev"
